pyhershey/__init__.py
pyhershey/database.toml.xz
pyhershey/display.py
pyhershey/glyph.py
pyhershey/glyph_factory.py
pyhershey/glyph_view.py
pyhershey/glyphfactory.py
pyhershey/plot.py
pyhershey/py.typed
pyhershey/shape_text.py
pyhershey/show.py
pyhershey/transformation.py
pyhershey-0.1.0.dist-info/AUTHORS.rst
pyhershey-0.1.0.dist-info/LICENSE.txt
pyhershey-0.1.0.dist-info/METADATA
pyhershey-0.1.0.dist-info/WHEEL
pyhershey-0.1.0.dist-info/top_level.txt
pyhershey-0.1.0.dist-info/RECORD
