Metadata-Version: 2.1
Name: pyhershey
Version: 0.1.0
Summary: pyhershey enable simple usage of Hershey fonts within python.
Home-page: https://gitlab.com/viggge/pyhershey
Author: viggge
License: GPLv3
Project-URL: Bug Reports, https://gitlab.com/viggge/pyhershey/-/issues
Project-URL: Source, https://gitlab.com/viggge/pyhershey
Project-URL: Documentation, https:/pyhershey.readthedocs.io/en/latest/
Platform: UNKNOWN
Requires-Python: >=3.8
Requires-Dist: toml
Provides-Extra: display
Requires-Dist: matplotlib ; extra == 'display'
Provides-Extra: docs
Requires-Dist: sphinx ; extra == 'docs'
Requires-Dist: pydata-sphinx-theme ; extra == 'docs'
Requires-Dist: sphinx-autoapi ; extra == 'docs'
Requires-Dist: matplotlib ; extra == 'docs'
Requires-Dist: sphinxcontrib-images ; extra == 'docs'
